iydon/__init__.py
iydon/base/__init__.py
iydon/base/constant.py
iydon/base/type.py
iydon/namespace/__init__.py
iydon/namespace/brief.py
iydon/namespace/full.py
iydon/namespace/private.py
iydon/test/__init__.py
iydon/test/test_glhf.py
iydon/test/test_rust.py
iydon/util/__init__.py
iydon/util/glhf/__init__.py
iydon/util/glhf/end.py
iydon/util/glhf/silver_bullet.py
iydon/util/rust/__init__.py
iydon/util/rust/std/__init__.py
iydon/util/rust/std/option.py
iydon/util/rust/std/result.py
iydon-2023.4.dist-info/LICENSE.txt
iydon-2023.4.dist-info/METADATA
iydon-2023.4.dist-info/WHEEL
iydon-2023.4.dist-info/RECORD
