Metadata-Version: 2.1
Name: iydon
Version: 2023.4
Summary: Iydon's common tools
Home-page: https://github.com/iydon/iydon
License: GPL-3.0-only
Keywords: utilities
Author: Iydon Liang
Author-email: liangiydon@gmail.com
Requires-Python: >=3.7,<4.0
Classifier: Environment :: Console
Classifier: License :: OSI Approved :: GNU General Public License v3 (GPLv3)
Classifier: Natural Language :: Chinese (Simplified)
Classifier: Natural Language :: English
Classifier: Operating System :: POSIX :: Linux
Classifier: Programming Language :: Python :: 3
Classifier: Programming Language :: Python :: 3.7
Classifier: Programming Language :: Python :: 3.8
Classifier: Programming Language :: Python :: 3.9
Classifier: Programming Language :: Python :: 3.10
Classifier: Programming Language :: Python :: 3.11
Classifier: Programming Language :: Python :: 3.10
Classifier: Programming Language :: Python :: 3.7
Classifier: Programming Language :: Python :: 3.8
Classifier: Programming Language :: Python :: 3.9
Classifier: Topic :: Software Development :: User Interfaces
Classifier: Topic :: Utilities
Classifier: Typing :: Typed
Provides-Extra: full
Provides-Extra: type
Requires-Dist: typing-extensions (>=4.5.0,<5.0.0) ; extra == "type" or extra == "full"
Project-URL: Bug Tracker, https://github.com/iydon/iydon/issues
Project-URL: Repository, https://github.com/iydon/iydon
